{
    "7974.T": {
        "last_close": 7003.0,
        "updated": true,
        "last_update_time": "2026-07-23 16:16:35"
    },
    "6501.T": {
        "last_close": 4807.0,
        "updated": true,
        "last_update_time": "2026-07-23 16:16:35"
    },
    "AAPL": {
        "last_close": 321.4800109863281,
        "updated": true,
        "last_update_time": "2026-07-23 16:16:58"
    },
    "MSFT": {
        "last_close": 380.25,
        "updated": true,
        "last_update_time": "2026-07-23 16:16:58"
    },
    "7203.T": {
        "last_close": 2939.0,
        "updated": true,
        "last_update_time": "2026-07-23 16:16:31"
    },
    "6758.T": {
        "last_close": 3444.0,
        "updated": true,
        "last_update_time": "2026-07-23 16:16:31"
    },
    "8035.T": {
        "last_close": 65960.0,
        "updated": true,
        "last_update_time": "2026-07-23 16:16:32"
    },
    "6861.T": {
        "last_close": 72110.0,
        "updated": true,
        "last_update_time": "2026-07-23 16:16:33"
    },
    "9983.T": {
        "last_close": 78580.0,
        "updated": true,
        "last_update_time": "2026-07-23 16:16:33"
    },
    "9432.T": {
        "last_close": 152.0,
        "updated": true,
        "last_update_time": "2026-07-23 16:16:34"
    },
    "9433.T": {
        "last_close": 2875.5,
        "updated": true,
        "last_update_time": "2026-07-23 16:16:34"
    },
    "8306.T": {
        "last_close": 3668.0,
        "updated": true,
        "last_update_time": "2026-07-23 16:16:35"
    },
    "8316.T": {
        "last_close": 7072.0,
        "updated": true,
        "last_update_time": "2026-07-23 16:16:35"
    },
    "4502.T": {
        "last_close": 5552.0,
        "updated": true,
        "last_update_time": "2026-07-23 16:16:35"
    },
    "6098.T": {
        "last_close": 12305.0,
        "updated": true,
        "last_update_time": "2026-07-23 16:16:35"
    },
    "9984.T": {
        "last_close": 5703.0,
        "updated": true,
        "last_update_time": "2026-07-23 16:16:36"
    },
    "8058.T": {
        "last_close": 4888.0,
        "updated": true,
        "last_update_time": "2026-07-23 16:16:36"
    },
    "8001.T": {
        "last_close": 1964.0,
        "updated": true,
        "last_update_time": "2026-07-23 16:16:36"
    },
    "8053.T": {
        "last_close": 1604.0,
        "updated": true,
        "last_update_time": "2026-07-23 16:16:36"
    },
    "8766.T": {
        "last_close": 7971.0,
        "updated": true,
        "last_update_time": "2026-07-23 16:16:36"
    },
    "4661.T": {
        "last_close": 2673.5,
        "updated": true,
        "last_update_time": "2026-07-23 16:16:37"
    },
    "6902.T": {
        "last_close": 1989.5,
        "updated": true,
        "last_update_time": "2026-07-23 16:16:37"
    },
    "6981.T": {
        "last_close": 8317.0,
        "updated": true,
        "last_update_time": "2026-07-23 16:16:37"
    },
    "6594.T": {
        "last_close": 2480.0,
        "updated": true,
        "last_update_time": "2026-07-23 16:16:37"
    },
    "7741.T": {
        "last_close": 25045.0,
        "updated": true,
        "last_update_time": "2026-07-23 16:16:38"
    },
    "9101.T": {
        "last_close": 5818.0,
        "updated": true,
        "last_update_time": "2026-07-23 16:16:38"
    },
    "9107.T": {
        "last_close": 2764.0,
        "updated": true,
        "last_update_time": "2026-07-23 16:16:38"
    },
    "9104.T": {
        "last_close": 5783.0,
        "updated": true,
        "last_update_time": "2026-07-23 16:16:38"
    },
    "5411.T": {
        "last_close": 1714.5,
        "updated": true,
        "last_update_time": "2026-07-23 16:16:38"
    },
    "5401.T": {
        "last_close": 599.0,
        "updated": true,
        "last_update_time": "2026-07-23 16:16:39"
    },
    "4503.T": {
        "last_close": 2175.5,
        "updated": true,
        "last_update_time": "2026-07-23 16:16:39"
    },
    "2503.T": {
        "last_close": 2906.0,
        "updated": true,
        "last_update_time": "2026-07-23 16:16:39"
    },
    "2502.T": {
        "last_close": 1629.5,
        "updated": true,
        "last_update_time": "2026-07-23 16:16:39"
    },
    "2914.T": {
        "last_close": 6458.0,
        "updated": true,
        "last_update_time": "2026-07-23 16:16:40"
    },
    "3382.T": {
        "last_close": 2092.0,
        "updated": true,
        "last_update_time": "2026-07-23 16:16:40"
    },
    "3092.T": {
        "last_close": 1135.0,
        "updated": true,
        "last_update_time": "2026-07-23 16:16:40"
    },
    "3289.T": {
        "last_close": 1338.5,
        "updated": true,
        "last_update_time": "2026-07-23 16:16:40"
    },
    "3407.T": {
        "last_close": 1857.0,
        "updated": true,
        "last_update_time": "2026-07-23 16:16:40"
    },
    "3401.T": {
        "last_close": 1710.5,
        "updated": true,
        "last_update_time": "2026-07-23 16:16:41"
    },
    "3861.T": {
        "last_close": 857.9000244140625,
        "updated": true,
        "last_update_time": "2026-07-23 16:16:41"
    },
    "3863.T": {
        "last_close": 1518.0,
        "updated": true,
        "last_update_time": "2026-07-23 16:16:42"
    },
    "4063.T": {
        "last_close": 7075.0,
        "updated": true,
        "last_update_time": "2026-07-23 16:16:42"
    },
    "4188.T": {
        "last_close": 1195.5,
        "updated": true,
        "last_update_time": "2026-07-23 16:16:43"
    },
    "4208.T": {
        "last_close": 3241.0,
        "updated": true,
        "last_update_time": "2026-07-23 16:16:44"
    },
    "4452.T": {
        "last_close": 3230.0,
        "updated": true,
        "last_update_time": "2026-07-23 16:16:44"
    },
    "4506.T": {
        "last_close": 1286.0,
        "updated": false,
        "last_update_time": "2026-07-23 00:16:56"
    },
    "4519.T": {
        "last_close": 7306.0,
        "updated": true,
        "last_update_time": "2026-07-23 16:16:45"
    },
    "4523.T": {
        "last_close": 4550.0,
        "updated": true,
        "last_update_time": "2026-07-23 16:16:45"
    },
    "4543.T": {
        "last_close": 2199.0,
        "updated": true,
        "last_update_time": "2026-07-23 16:16:45"
    },
    "4578.T": {
        "last_close": 10970.0,
        "updated": true,
        "last_update_time": "2026-07-23 16:16:45"
    },
    "4901.T": {
        "last_close": 3665.0,
        "updated": true,
        "last_update_time": "2026-07-23 16:16:46"
    },
    "4911.T": {
        "last_close": 3040.0,
        "updated": true,
        "last_update_time": "2026-07-23 16:16:46"
    },
    "5020.T": {
        "last_close": 1320.0,
        "updated": true,
        "last_update_time": "2026-07-23 16:16:46"
    },
    "5108.T": {
        "last_close": 3769.0,
        "updated": true,
        "last_update_time": "2026-07-23 16:16:46"
    },
    "5201.T": {
        "last_close": 6344.0,
        "updated": true,
        "last_update_time": "2026-07-23 16:16:46"
    },
    "5214.T": {
        "last_close": 5718.0,
        "updated": true,
        "last_update_time": "2026-07-23 16:16:47"
    },
    "5332.T": {
        "last_close": 7606.0,
        "updated": true,
        "last_update_time": "2026-07-23 16:16:47"
    },
    "5406.T": {
        "last_close": 1984.5,
        "updated": true,
        "last_update_time": "2026-07-23 16:16:47"
    },
    "5713.T": {
        "last_close": 7521.0,
        "updated": true,
        "last_update_time": "2026-07-23 16:16:47"
    },
    "5802.T": {
        "last_close": 2451.0,
        "updated": true,
        "last_update_time": "2026-07-23 16:16:48"
    },
    "5803.T": {
        "last_close": 4751.0,
        "updated": true,
        "last_update_time": "2026-07-23 16:16:48"
    },
    "5901.T": {
        "last_close": 4119.0,
        "updated": true,
        "last_update_time": "2026-07-23 16:16:48"
    },
    "6099.T": {
        "last_close": 783.0,
        "updated": true,
        "last_update_time": "2026-07-23 16:16:48"
    },
    "6301.T": {
        "last_close": 6447.0,
        "updated": true,
        "last_update_time": "2026-07-23 16:16:48"
    },
    "6367.T": {
        "last_close": 24240.0,
        "updated": true,
        "last_update_time": "2026-07-23 16:16:49"
    },
    "6471.T": {
        "last_close": 1133.5,
        "updated": true,
        "last_update_time": "2026-07-23 16:16:49"
    },
    "6473.T": {
        "last_close": 2062.5,
        "updated": true,
        "last_update_time": "2026-07-23 16:16:49"
    },
    "6503.T": {
        "last_close": 5629.0,
        "updated": true,
        "last_update_time": "2026-07-23 16:16:49"
    },
    "6504.T": {
        "last_close": 12935.0,
        "updated": true,
        "last_update_time": "2026-07-23 16:16:49"
    },
    "6506.T": {
        "last_close": 5213.0,
        "updated": true,
        "last_update_time": "2026-07-23 16:16:50"
    },
    "6586.T": {
        "last_close": 5657.0,
        "updated": true,
        "last_update_time": "2026-07-23 16:16:50"
    },
    "6645.T": {
        "last_close": 5463.0,
        "updated": true,
        "last_update_time": "2026-07-23 16:16:50"
    },
    "6674.T": {
        "last_close": 5914.0,
        "updated": true,
        "last_update_time": "2026-07-23 16:16:50"
    },
    "6723.T": {
        "last_close": 4175.0,
        "updated": true,
        "last_update_time": "2026-07-23 16:16:51"
    },
    "6752.T": {
        "last_close": 4095.0,
        "updated": true,
        "last_update_time": "2026-07-23 16:16:51"
    },
    "6754.T": {
        "last_close": 3934.0,
        "updated": true,
        "last_update_time": "2026-07-23 16:16:51"
    },
    "6762.T": {
        "last_close": 3107.0,
        "updated": true,
        "last_update_time": "2026-07-23 16:16:51"
    },
    "6770.T": {
        "last_close": 2126.0,
        "updated": true,
        "last_update_time": "2026-07-23 16:16:51"
    },
    "6841.T": {
        "last_close": 5727.0,
        "updated": true,
        "last_update_time": "2026-07-23 16:16:52"
    },
    "6857.T": {
        "last_close": 29585.0,
        "updated": true,
        "last_update_time": "2026-07-23 16:16:52"
    },
    "6901.T": {
        "last_close": 1296.0,
        "updated": false,
        "last_update_time": null
    },
    "6954.T": {
        "last_close": 6873.0,
        "updated": true,
        "last_update_time": "2026-07-23 16:16:53"
    },
    "6971.T": {
        "last_close": 3780.0,
        "updated": true,
        "last_update_time": "2026-07-23 16:16:53"
    },
    "7011.T": {
        "last_close": 3892.0,
        "updated": true,
        "last_update_time": "2026-07-23 16:16:53"
    },
    "7012.T": {
        "last_close": 2736.5,
        "updated": true,
        "last_update_time": "2026-07-23 16:16:53"
    },
    "7201.T": {
        "last_close": 334.29998779296875,
        "updated": true,
        "last_update_time": "2026-07-23 16:16:53"
    },
    "7267.T": {
        "last_close": 1559.0,
        "updated": true,
        "last_update_time": "2026-07-23 16:16:54"
    },
    "7270.T": {
        "last_close": 2583.0,
        "updated": true,
        "last_update_time": "2026-07-23 16:16:54"
    },
    "7731.T": {
        "last_close": 2212.5,
        "updated": true,
        "last_update_time": "2026-07-23 16:16:54"
    },
    "7733.T": {
        "last_close": 1726.0,
        "updated": true,
        "last_update_time": "2026-07-23 16:16:54"
    },
    "7751.T": {
        "last_close": 4536.0,
        "updated": true,
        "last_update_time": "2026-07-23 16:16:55"
    },
    "8031.T": {
        "last_close": 4911.0,
        "updated": true,
        "last_update_time": "2026-07-23 16:16:55"
    },
    "8113.T": {
        "last_close": 960.5999755859375,
        "updated": true,
        "last_update_time": "2026-07-23 16:16:55"
    },
    "8267.T": {
        "last_close": 1357.5,
        "updated": true,
        "last_update_time": "2026-07-23 16:16:55"
    },
    "8308.T": {
        "last_close": 2322.0,
        "updated": true,
        "last_update_time": "2026-07-23 16:16:55"
    },
    "8411.T": {
        "last_close": 8529.0,
        "updated": true,
        "last_update_time": "2026-07-23 16:16:55"
    },
    "8591.T": {
        "last_close": 6582.0,
        "updated": true,
        "last_update_time": "2026-07-23 16:16:56"
    },
    "8769.T": {
        "last_close": 514.0,
        "updated": false,
        "last_update_time": "2026-07-23 00:17:18"
    },
    "8802.T": {
        "last_close": 4204.0,
        "updated": true,
        "last_update_time": "2026-07-23 16:16:56"
    },
    "9020.T": {
        "last_close": 3617.0,
        "updated": true,
        "last_update_time": "2026-07-23 16:16:57"
    },
    "9022.T": {
        "last_close": 3796.0,
        "updated": true,
        "last_update_time": "2026-07-23 16:16:58"
    },
    "9021.T": {
        "last_close": 2939.0,
        "updated": true,
        "last_update_time": "2026-07-23 16:16:58"
    },
    "AMZN": {
        "last_close": 234.05999755859375,
        "updated": true,
        "last_update_time": "2026-07-23 16:16:59"
    },
    "NVDA": {
        "last_close": 208.94000244140625,
        "updated": true,
        "last_update_time": "2026-07-23 16:16:59"
    },
    "META": {
        "last_close": 603.02001953125,
        "updated": true,
        "last_update_time": "2026-07-23 16:16:59"
    },
    "GOOGL": {
        "last_close": 320.5400085449219,
        "updated": true,
        "last_update_time": "2026-07-23 16:16:59"
    },
    "GOOG": {
        "last_close": 320.2799987792969,
        "updated": true,
        "last_update_time": "2026-07-23 16:16:59"
    },
    "TSLA": {
        "last_close": 325.1099853515625,
        "updated": true,
        "last_update_time": "2026-07-23 16:16:59"
    },
    "UNH": {
        "last_close": 422.260009765625,
        "updated": true,
        "last_update_time": "2026-07-23 16:17:00"
    },
    "XOM": {
        "last_close": 157.5500030517578,
        "updated": true,
        "last_update_time": "2026-07-23 16:17:00"
    },
    "JNJ": {
        "last_close": 258.9750061035156,
        "updated": true,
        "last_update_time": "2026-07-23 16:17:01"
    },
    "JPM": {
        "last_close": 347.9200134277344,
        "updated": true,
        "last_update_time": "2026-07-23 16:17:01"
    },
    "V": {
        "last_close": 350.2200012207031,
        "updated": true,
        "last_update_time": "2026-07-23 16:17:01"
    },
    "PG": {
        "last_close": 146.5050048828125,
        "updated": true,
        "last_update_time": "2026-07-23 16:17:01"
    },
    "MA": {
        "last_close": 527.2515258789062,
        "updated": true,
        "last_update_time": "2026-07-23 16:17:02"
    },
    "HD": {
        "last_close": 325.5199890136719,
        "updated": true,
        "last_update_time": "2026-07-23 16:17:02"
    },
    "CVX": {
        "last_close": 196.52000427246094,
        "updated": true,
        "last_update_time": "2026-07-23 16:17:02"
    },
    "MRK": {
        "last_close": 130.9600067138672,
        "updated": true,
        "last_update_time": "2026-07-23 16:17:02"
    },
    "ABBV": {
        "last_close": 257.44000244140625,
        "updated": true,
        "last_update_time": "2026-07-23 16:17:03"
    },
    "PEP": {
        "last_close": 134.80999755859375,
        "updated": true,
        "last_update_time": "2026-07-23 16:17:03"
    },
    "KO": {
        "last_close": 81.125,
        "updated": true,
        "last_update_time": "2026-07-23 16:17:04"
    },
    "AVGO": {
        "last_close": 390.0299987792969,
        "updated": true,
        "last_update_time": "2026-07-23 16:17:04"
    },
    "COST": {
        "last_close": 919.0999755859375,
        "updated": true,
        "last_update_time": "2026-07-23 16:17:04"
    },
    "WMT": {
        "last_close": 107.97000122070312,
        "updated": true,
        "last_update_time": "2026-07-23 16:17:04"
    },
    "BAC": {
        "last_close": 61.0099983215332,
        "updated": true,
        "last_update_time": "2026-07-23 16:17:04"
    },
    "DIS": {
        "last_close": 93.0,
        "updated": true,
        "last_update_time": "2026-07-23 16:17:05"
    },
    "MCD": {
        "last_close": 262.875,
        "updated": true,
        "last_update_time": "2026-07-23 16:17:05"
    },
    "CSCO": {
        "last_close": 113.11000061035156,
        "updated": true,
        "last_update_time": "2026-07-23 16:17:06"
    },
    "PFE": {
        "last_close": 25.014999389648438,
        "updated": true,
        "last_update_time": "2026-07-23 16:17:06"
    },
    "TMO": {
        "last_close": 575.6500244140625,
        "updated": true,
        "last_update_time": "2026-07-23 16:17:07"
    },
    "ACN": {
        "last_close": 138.06500244140625,
        "updated": true,
        "last_update_time": "2026-07-23 16:17:07"
    },
    "DHR": {
        "last_close": 189.7100067138672,
        "updated": true,
        "last_update_time": "2026-07-23 16:17:08"
    },
    "LIN": {
        "last_close": 507.0350036621094,
        "updated": true,
        "last_update_time": "2026-07-23 16:17:10"
    },
    "WFC": {
        "last_close": 86.08999633789062,
        "updated": true,
        "last_update_time": "2026-07-23 16:17:10"
    },
    "TXN": {
        "last_close": 282.2550048828125,
        "updated": true,
        "last_update_time": "2026-07-23 16:17:10"
    },
    "UPS": {
        "last_close": 114.54499816894531,
        "updated": true,
        "last_update_time": "2026-07-23 16:17:10"
    },
    "NEE": {
        "last_close": 89.94000244140625,
        "updated": true,
        "last_update_time": "2026-07-23 16:17:11"
    },
    "RTX": {
        "last_close": 210.39999389648438,
        "updated": true,
        "last_update_time": "2026-07-23 16:17:11"
    },
    "IBM": {
        "last_close": 206.75,
        "updated": true,
        "last_update_time": "2026-07-23 16:17:11"
    },
    "INTC": {
        "last_close": 101.25,
        "updated": true,
        "last_update_time": "2026-07-23 16:17:12"
    },
    "AMD": {
        "last_close": 541.1849975585938,
        "updated": true,
        "last_update_time": "2026-07-23 16:17:12"
    },
    "NFLX": {
        "last_close": 68.4000015258789,
        "updated": true,
        "last_update_time": "2026-07-23 16:17:12"
    },
    "QCOM": {
        "last_close": 169.50999450683594,
        "updated": true,
        "last_update_time": "2026-07-23 16:17:12"
    },
    "SBUX": {
        "last_close": 102.6500015258789,
        "updated": true,
        "last_update_time": "2026-07-23 16:17:13"
    },
    "AMAT": {
        "last_close": 565.0850219726562,
        "updated": true,
        "last_update_time": "2026-07-23 16:17:13"
    },
    "LOW": {
        "last_close": 201.16000366210938,
        "updated": true,
        "last_update_time": "2026-07-23 16:17:13"
    },
    "CAT": {
        "last_close": 907.030029296875,
        "updated": true,
        "last_update_time": "2026-07-23 16:17:13"
    },
    "BLK": {
        "last_close": 1041.739990234375,
        "updated": true,
        "last_update_time": "2026-07-23 16:17:14"
    },
    "GE": {
        "last_close": 348.6099853515625,
        "updated": true,
        "last_update_time": "2026-07-23 16:17:14"
    },
    "HON": {
        "last_close": 248.25,
        "updated": true,
        "last_update_time": "2026-07-23 16:17:14"
    },
    "BA": {
        "last_close": 208.64999389648438,
        "updated": false,
        "last_update_time": "2026-07-22 20:45:51"
    },
    "MDT": {
        "last_close": 82.11000061035156,
        "updated": true,
        "last_update_time": "2026-07-23 16:17:15"
    },
    "SPGI": {
        "last_close": 420.6400146484375,
        "updated": true,
        "last_update_time": "2026-07-23 16:17:15"
    },
    "GS": {
        "last_close": 1072.9300537109375,
        "updated": true,
        "last_update_time": "2026-07-23 16:17:15"
    },
    "PLD": {
        "last_close": 143.81500244140625,
        "updated": true,
        "last_update_time": "2026-07-23 16:17:15"
    },
    "ADBE": {
        "last_close": 213.3000030517578,
        "updated": true,
        "last_update_time": "2026-07-23 16:17:15"
    },
    "NOW": {
        "last_close": 94.5250015258789,
        "updated": true,
        "last_update_time": "2026-07-23 16:17:16"
    },
    "BKNG": {
        "last_close": 172.64999389648438,
        "updated": true,
        "last_update_time": "2026-07-23 16:17:16"
    },
    "ISRG": {
        "last_close": 332.3699951171875,
        "updated": true,
        "last_update_time": "2026-07-23 16:17:16"
    },
    "LMT": {
        "last_close": 573.8800048828125,
        "updated": true,
        "last_update_time": "2026-07-23 16:17:16"
    },
    "EL": {
        "last_close": 79.5250015258789,
        "updated": true,
        "last_update_time": "2026-07-23 16:17:16"
    },
    "MO": {
        "last_close": 71.92500305175781,
        "updated": true,
        "last_update_time": "2026-07-23 16:17:17"
    },
    "DE": {
        "last_close": 614.0700073242188,
        "updated": true,
        "last_update_time": "2026-07-23 16:17:17"
    },
    "C": {
        "last_close": 131.88999938964844,
        "updated": true,
        "last_update_time": "2026-07-23 16:17:17"
    },
    "T": {
        "last_close": 22.95639991760254,
        "updated": true,
        "last_update_time": "2026-07-23 16:17:18"
    },
    "VZ": {
        "last_close": 44.095001220703125,
        "updated": true,
        "last_update_time": "2026-07-23 16:17:18"
    },
    "FDX": {
        "last_close": 315.885009765625,
        "updated": true,
        "last_update_time": "2026-07-23 16:17:18"
    },
    "SO": {
        "last_close": 96.14990234375,
        "updated": true,
        "last_update_time": "2026-07-23 16:17:18"
    },
    "DUK": {
        "last_close": 128.86500549316406,
        "updated": true,
        "last_update_time": "2026-07-23 16:17:18"
    },
    "AEP": {
        "last_close": 134.43499755859375,
        "updated": true,
        "last_update_time": "2026-07-23 16:17:19"
    },
    "REGN": {
        "last_close": 652.2750244140625,
        "updated": true,
        "last_update_time": "2026-07-23 16:17:19"
    },
    "GILD": {
        "last_close": 130.2071075439453,
        "updated": true,
        "last_update_time": "2026-07-23 16:17:19"
    },
    "VRTX": {
        "last_close": 476.68499755859375,
        "updated": true,
        "last_update_time": "2026-07-23 16:17:19"
    },
    "CSX": {
        "last_close": 52.2400016784668,
        "updated": true,
        "last_update_time": "2026-07-23 16:17:19"
    },
    "NSC": {
        "last_close": 347.5700988769531,
        "updated": true,
        "last_update_time": "2026-07-23 16:17:20"
    },
    "BDX": {
        "last_close": 153.0850067138672,
        "updated": true,
        "last_update_time": "2026-07-23 16:17:21"
    },
    "CL": {
        "last_close": 89.80000305175781,
        "updated": true,
        "last_update_time": "2026-07-23 16:17:21"
    },
    "MNST": {
        "last_close": 93.37999725341797,
        "updated": true,
        "last_update_time": "2026-07-23 16:17:21"
    },
    "KDP": {
        "last_close": 29.7450008392334,
        "updated": true,
        "last_update_time": "2026-07-23 16:17:21"
    },
    "WM": {
        "last_close": 237.5500030517578,
        "updated": true,
        "last_update_time": "2026-07-23 16:17:21"
    },
    "ADP": {
        "last_close": 240.89999389648438,
        "updated": true,
        "last_update_time": "2026-07-23 16:17:22"
    },
    "ORCL": {
        "last_close": 120.83000183105469,
        "updated": true,
        "last_update_time": "2026-07-23 16:17:22"
    },
    "CRM": {
        "last_close": 157.74169921875,
        "updated": true,
        "last_update_time": "2026-07-23 16:17:22"
    },
    "PANW": {
        "last_close": 324.4200134277344,
        "updated": true,
        "last_update_time": "2026-07-23 16:17:22"
    },
    "FTNT": {
        "last_close": 151.80999755859375,
        "updated": true,
        "last_update_time": "2026-07-23 16:17:22"
    },
    "HCA": {
        "last_close": 374.6700134277344,
        "updated": true,
        "last_update_time": "2026-07-23 16:17:22"
    },
    "LRCX": {
        "last_close": 319.875,
        "updated": true,
        "last_update_time": "2026-07-23 16:17:22"
    },
    "MU": {
        "last_close": 990.0,
        "updated": true,
        "last_update_time": "2026-07-23 16:17:23"
    },
    "ZTS": {
        "last_close": 74.05000305175781,
        "updated": true,
        "last_update_time": "2026-07-23 16:17:23"
    },
    "MAR": {
        "last_close": 363.2650146484375,
        "updated": true,
        "last_update_time": "2026-07-23 16:17:23"
    },
    "ETN": {
        "last_close": 414.3550109863281,
        "updated": true,
        "last_update_time": "2026-07-23 16:17:23"
    },
    "EMR": {
        "last_close": 143.63499450683594,
        "updated": true,
        "last_update_time": "2026-07-23 16:17:24"
    },
    "ROST": {
        "last_close": 234.25,
        "updated": true,
        "last_update_time": "2026-07-23 16:17:24"
    },
    "TJX": {
        "last_close": 153.44500732421875,
        "updated": true,
        "last_update_time": "2026-07-23 16:17:25"
    }
}